maturin_watchdog/plugin.py
maturin_watchdog-0.1.20.dist-info/METADATA
maturin_watchdog-0.1.20.dist-info/WHEEL
maturin_watchdog-0.1.20.dist-info/entry_points.txt
maturin_watchdog-0.1.20.dist-info/RECORD
