Metadata-Version: 2.1
Name: maturin-watchdog
Version: 0.1.20
Summary: Build via maturin when changes are detected
Author: Jocelyn-Gas
Author-email: jocelyn.gas@dillygence.com
Requires-Python: >=3.11,<4.0
Classifier: Programming Language :: Python :: 3
Classifier: Programming Language :: Python :: 3.11
Classifier: Programming Language :: Python :: 3.12
Requires-Dist: poetry (>=1.8.2,<2.0.0)
Requires-Dist: python-dotenv (>=1.0.1,<2.0.0)
